{
  "tournaments": [
    {
      "id": 7097762,
      "name": "t",
      "start date": "1888-10-23",
      "location": "t",
      "description": "tournoi d'\u00e9chec",
      "players": [
        {
          "last_name": "Dupont",
          "first_name": "Jean",
          "date_of_birth": "1990-05-12",
          "id": "YR27653",
          "score": 0
        },
        {
          "last_name": "Martin",
          "first_name": "Sophie",
          "date_of_birth": "1998-02-28",
          "id": "YR34681",
          "score": 0.5
        },
        {
          "last_name": "Garcia",
          "first_name": "Pablo",
          "date_of_birth": "1987-07-19",
          "id": "DT91027",
          "score": 1
        },
        {
          "last_name": "Lefebvre",
          "first_name": "Camille",
          "date_of_birth": "2000-01-03",
          "id": "TF52376",
          "score": 0.5
        },
        {
          "last_name": "Nguyen",
          "first_name": "Thierry",
          "date_of_birth": "1985-11-11",
          "id": "CT83941",
          "score": 0.5
        },
        {
          "last_name": "Moreau",
          "first_name": "Luc",
          "date_of_birth": "1984-04-22",
          "id": "KX57234",
          "score": 0.5
        },
        {
          "last_name": "Caron",
          "first_name": "Antoine",
          "date_of_birth": "1991-04-16",
          "id": "LE65874",
          "score": 0.5
        },
        {
          "last_name": "Fontaine",
          "first_name": "David",
          "date_of_birth": "1985-01-14",
          "id": "ZD22348",
          "score": 0.5
        }
      ],
      "rounds": [
        {
          "start_date": "30/10/2020",
          "end_date": null,
          "games": [
            [
              {
                "player1": {
                  "last_name": "Garcia",
                  "first_name": "Pablo",
                  "date_of_birth": "1987-07-19",
                  "id": "DT91027"
                },
                "score": 1
              },
              {
                "player2": {
                  "last_name": "Dupont",
                  "first_name": "Jean",
                  "date_of_birth": "1990-05-12",
                  "id": "YR27653"
                },
                "score": 0
              }
            ],
            [
              {
                "player1": {
                  "last_name": "Nguyen",
                  "first_name": "Thierry",
                  "date_of_birth": "1985-11-11",
                  "id": "CT83941"
                },
                "score": 0.5
              },
              {
                "player2": {
                  "last_name": "Lefebvre",
                  "first_name": "Camille",
                  "date_of_birth": "2000-01-03",
                  "id": "TF52376"
                },
                "score": 0.5
              }
            ],
            [
              {
                "player1": {
                  "last_name": "Fontaine",
                  "first_name": "David",
                  "date_of_birth": "1985-01-14",
                  "id": "ZD22348"
                },
                "score": 0.5
              },
              {
                "player2": {
                  "last_name": "Martin",
                  "first_name": "Sophie",
                  "date_of_birth": "1998-02-28",
                  "id": "YR34681"
                },
                "score": 0.5
              }
            ],
            [
              {
                "player1": {
                  "last_name": "Moreau",
                  "first_name": "Luc",
                  "date_of_birth": "1984-04-22",
                  "id": "KX57234"
                },
                "score": 0.5
              },
              {
                "player2": {
                  "last_name": "Caron",
                  "first_name": "Antoine",
                  "date_of_birth": "1991-04-16",
                  "id": "LE65874"
                },
                "score": 0.5
              }
            ]
          ],
          "round_number": 1,
          "closed": true
        }
      ]
    },
    {
      "id": 6012711,
      "name": "1",
      "start date": "1555-10-23",
      "location": "2",
      "description": "tournoi d'\u00e9chec",
      "players": [
        {
          "last_name": "Dupont",
          "first_name": "Jean",
          "date_of_birth": "1990-05-12",
          "id": "YR27653",
          "score": 0.5
        },
        {
          "last_name": "Martin",
          "first_name": "Sophie",
          "date_of_birth": "1998-02-28",
          "id": "YR34681",
          "score": 0.5
        },
        {
          "last_name": "Garcia",
          "first_name": "Pablo",
          "date_of_birth": "1987-07-19",
          "id": "DT91027",
          "score": 0
        },
        {
          "last_name": "Lefebvre",
          "first_name": "Camille",
          "date_of_birth": "2000-01-03",
          "id": "TF52376",
          "score": 1
        },
        {
          "last_name": "Nguyen",
          "first_name": "Thierry",
          "date_of_birth": "1985-11-11",
          "id": "CT83941",
          "score": 1
        },
        {
          "last_name": "Moreau",
          "first_name": "Luc",
          "date_of_birth": "1984-04-22",
          "id": "KX57234",
          "score": 0
        },
        {
          "last_name": "Caron",
          "first_name": "Antoine",
          "date_of_birth": "1991-04-16",
          "id": "LE65874",
          "score": 0
        },
        {
          "last_name": "Fontaine",
          "first_name": "David",
          "date_of_birth": "1985-01-14",
          "id": "ZD22348",
          "score": 1
        }
      ],
      "rounds": [
        {
          "start_date": "30/10/2020",
          "end_date": null,
          "games": [
            [
              {
                "player1": {
                  "last_name": "Fontaine",
                  "first_name": "David",
                  "date_of_birth": "1985-01-14",
                  "id": "ZD22348"
                },
                "score": 1
              },
              {
                "player2": {
                  "last_name": "Caron",
                  "first_name": "Antoine",
                  "date_of_birth": "1991-04-16",
                  "id": "LE65874"
                },
                "score": 0
              }
            ],
            [
              {
                "player1": {
                  "last_name": "Nguyen",
                  "first_name": "Thierry",
                  "date_of_birth": "1985-11-11",
                  "id": "CT83941"
                },
                "score": 1
              },
              {
                "player2": {
                  "last_name": "Moreau",
                  "first_name": "Luc",
                  "date_of_birth": "1984-04-22",
                  "id": "KX57234"
                },
                "score": 0
              }
            ],
            [
              {
                "player1": {
                  "last_name": "Martin",
                  "first_name": "Sophie",
                  "date_of_birth": "1998-02-28",
                  "id": "YR34681"
                },
                "score": 0.5
              },
              {
                "player2": {
                  "last_name": "Dupont",
                  "first_name": "Jean",
                  "date_of_birth": "1990-05-12",
                  "id": "YR27653"
                },
                "score": 0.5
              }
            ],
            [
              {
                "player1": {
                  "last_name": "Garcia",
                  "first_name": "Pablo",
                  "date_of_birth": "1987-07-19",
                  "id": "DT91027"
                },
                "score": 0
              },
              {
                "player2": {
                  "last_name": "Lefebvre",
                  "first_name": "Camille",
                  "date_of_birth": "2000-01-03",
                  "id": "TF52376"
                },
                "score": 1
              }
            ]
          ],
          "round_number": 1,
          "closed": true
        }
      ]
    },
    {
      "id": 6868236,
      "name": "a",
      "start date": "1996-10-23",
      "location": "a",
      "description": "tournoi d'\u00e9chec",
      "players": [
        {
          "last_name": "Dupont",
          "first_name": "Jean",
          "date_of_birth": "1990-05-12",
          "id": "YR27653",
          "score": 4
        },
        {
          "last_name": "Martin",
          "first_name": "Sophie",
          "date_of_birth": "1998-02-28",
          "id": "YR34681",
          "score": 2.5
        },
        {
          "last_name": "Garcia",
          "first_name": "Pablo",
          "date_of_birth": "1987-07-19",
          "id": "DT91027",
          "score": 1.5
        },
        {
          "last_name": "Lefebvre",
          "first_name": "Camille",
          "date_of_birth": "2000-01-03",
          "id": "TF52376",
          "score": 2.0
        },
        {
          "last_name": "Nguyen",
          "first_name": "Thierry",
          "date_of_birth": "1985-11-11",
          "id": "CT83941",
          "score": 0.5
        },
        {
          "last_name": "Moreau",
          "first_name": "Luc",
          "date_of_birth": "1984-04-22",
          "id": "KX57234",
          "score": 1.5
        },
        {
          "last_name": "Caron",
          "first_name": "Antoine",
          "date_of_birth": "1991-04-16",
          "id": "LE65874",
          "score": 2.0
        },
        {
          "last_name": "Fontaine",
          "first_name": "David",
          "date_of_birth": "1985-01-14",
          "id": "ZD22348",
          "score": 2.0
        }
      ],
      "rounds": [
        {
          "start_date": "30/10/2020",
          "end_date": null,
          "games": [
            [
              {
                "player1": {
                  "last_name": "Dupont",
                  "first_name": "Jean",
                  "date_of_birth": "1990-05-12",
                  "id": "YR27653"
                },
                "score": 1
              },
              {
                "player2": {
                  "last_name": "Moreau",
                  "first_name": "Luc",
                  "date_of_birth": "1984-04-22",
                  "id": "KX57234"
                },
                "score": 0
              }
            ],
            [
              {
                "player1": {
                  "last_name": "Fontaine",
                  "first_name": "David",
                  "date_of_birth": "1985-01-14",
                  "id": "ZD22348"
                },
                "score": 0.5
              },
              {
                "player2": {
                  "last_name": "Garcia",
                  "first_name": "Pablo",
                  "date_of_birth": "1987-07-19",
                  "id": "DT91027"
                },
                "score": 0.5
              }
            ],
            [
              {
                "player1": {
                  "last_name": "Martin",
                  "first_name": "Sophie",
                  "date_of_birth": "1998-02-28",
                  "id": "YR34681"
                },
                "score": 0.5
              },
              {
                "player2": {
                  "last_name": "Lefebvre",
                  "first_name": "Camille",
                  "date_of_birth": "2000-01-03",
                  "id": "TF52376"
                },
                "score": 0.5
              }
            ],
            [
              {
                "player1": {
                  "last_name": "Caron",
                  "first_name": "Antoine",
                  "date_of_birth": "1991-04-16",
                  "id": "LE65874"
                },
                "score": 1
              },
              {
                "player2": {
                  "last_name": "Nguyen",
                  "first_name": "Thierry",
                  "date_of_birth": "1985-11-11",
                  "id": "CT83941"
                },
                "score": 0
              }
            ]
          ],
          "round_number": 1,
          "closed": true
        },
        {
          "start_date": "30/10/2020",
          "end_date": null,
          "games": [
            [
              {
                "player1": {
                  "last_name": "Dupont",
                  "first_name": "Jean",
                  "date_of_birth": "1990-05-12",
                  "id": "YR27653",
                  "score": 1
                },
                "score": 1
              },
              {
                "player2": {
                  "last_name": "Caron",
                  "first_name": "Antoine",
                  "date_of_birth": "1991-04-16",
                  "id": "LE65874",
                  "score": 1
                },
                "score": 0
              }
            ],
            [
              {
                "player1": {
                  "last_name": "Fontaine",
                  "first_name": "David",
                  "date_of_birth": "1985-01-14",
                  "id": "ZD22348",
                  "score": 0.5
                },
                "score": 1
              },
              {
                "player2": {
                  "last_name": "Garcia",
                  "first_name": "Pablo",
                  "date_of_birth": "1987-07-19",
                  "id": "DT91027",
                  "score": 0.5
                },
                "score": 0
              }
            ],
            [
              {
                "player1": {
                  "last_name": "Martin",
                  "first_name": "Sophie",
                  "date_of_birth": "1998-02-28",
                  "id": "YR34681",
                  "score": 0.5
                },
                "score": 1
              },
              {
                "player2": {
                  "last_name": "Lefebvre",
                  "first_name": "Camille",
                  "date_of_birth": "2000-01-03",
                  "id": "TF52376",
                  "score": 0.5
                },
                "score": 0
              }
            ],
            [
              {
                "player1": {
                  "last_name": "Moreau",
                  "first_name": "Luc",
                  "date_of_birth": "1984-04-22",
                  "id": "KX57234",
                  "score": 0
                },
                "score": 1
              },
              {
                "player2": {
                  "last_name": "Nguyen",
                  "first_name": "Thierry",
                  "date_of_birth": "1985-11-11",
                  "id": "CT83941",
                  "score": 0
                },
                "score": 0
              }
            ]
          ],
          "round_number": 2,
          "closed": true
        },
        {
          "start_date": "30/10/2020",
          "end_date": null,
          "games": [
            [
              {
                "player1": {
                  "last_name": "Dupont",
                  "first_name": "Jean",
                  "date_of_birth": "1990-05-12",
                  "id": "YR27653",
                  "score": 2
                },
                "score": 1
              },
              {
                "player2": {
                  "last_name": "Fontaine",
                  "first_name": "David",
                  "date_of_birth": "1985-01-14",
                  "id": "ZD22348",
                  "score": 1.5
                },
                "score": 0
              }
            ],
            [
              {
                "player1": {
                  "last_name": "Martin",
                  "first_name": "Sophie",
                  "date_of_birth": "1998-02-28",
                  "id": "YR34681",
                  "score": 1.5
                },
                "score": 1
              },
              {
                "player2": {
                  "last_name": "Moreau",
                  "first_name": "Luc",
                  "date_of_birth": "1984-04-22",
                  "id": "KX57234",
                  "score": 1
                },
                "score": 0
              }
            ],
            [
              {
                "player1": {
                  "last_name": "Caron",
                  "first_name": "Antoine",
                  "date_of_birth": "1991-04-16",
                  "id": "LE65874",
                  "score": 1
                },
                "score": 0.5
              },
              {
                "player2": {
                  "last_name": "Garcia",
                  "first_name": "Pablo",
                  "date_of_birth": "1987-07-19",
                  "id": "DT91027",
                  "score": 0.5
                },
                "score": 0.5
              }
            ],
            [
              {
                "player1": {
                  "last_name": "Lefebvre",
                  "first_name": "Camille",
                  "date_of_birth": "2000-01-03",
                  "id": "TF52376",
                  "score": 0.5
                },
                "score": 1
              },
              {
                "player2": {
                  "last_name": "Nguyen",
                  "first_name": "Thierry",
                  "date_of_birth": "1985-11-11",
                  "id": "CT83941",
                  "score": 0
                },
                "score": 0
              }
            ]
          ],
          "round_number": 3,
          "closed": true
        },
        {
          "start_date": "30/10/2020",
          "end_date": null,
          "games": [
            [
              {
                "player1": {
                  "last_name": "Dupont",
                  "first_name": "Jean",
                  "date_of_birth": "1990-05-12",
                  "id": "YR27653",
                  "score": 3
                },
                "score": 1
              },
              {
                "player2": {
                  "last_name": "Martin",
                  "first_name": "Sophie",
                  "date_of_birth": "1998-02-28",
                  "id": "YR34681",
                  "score": 2.5
                },
                "score": 0
              }
            ],
            [
              {
                "player1": {
                  "last_name": "Fontaine",
                  "first_name": "David",
                  "date_of_birth": "1985-01-14",
                  "id": "ZD22348",
                  "score": 1.5
                },
                "score": 0.5
              },
              {
                "player2": {
                  "last_name": "Lefebvre",
                  "first_name": "Camille",
                  "date_of_birth": "2000-01-03",
                  "id": "TF52376",
                  "score": 1.5
                },
                "score": 0.5
              }
            ],
            [
              {
                "player1": {
                  "last_name": "Caron",
                  "first_name": "Antoine",
                  "date_of_birth": "1991-04-16",
                  "id": "LE65874",
                  "score": 1.5
                },
                "score": 0.5
              },
              {
                "player2": {
                  "last_name": "Moreau",
                  "first_name": "Luc",
                  "date_of_birth": "1984-04-22",
                  "id": "KX57234",
                  "score": 1
                },
                "score": 0.5
              }
            ],
            [
              {
                "player1": {
                  "last_name": "Garcia",
                  "first_name": "Pablo",
                  "date_of_birth": "1987-07-19",
                  "id": "DT91027",
                  "score": 1.0
                },
                "score": 0.5
              },
              {
                "player2": {
                  "last_name": "Nguyen",
                  "first_name": "Thierry",
                  "date_of_birth": "1985-11-11",
                  "id": "CT83941",
                  "score": 0
                },
                "score": 0.5
              }
            ]
          ],
          "round_number": 4,
          "closed": false
        }
      ]
    }
  ]
}
